<?xml version="1.0" encoding="UTF-8"?>
<translations>
    <!-- Modul-Titel -->
    <module_title>ISPConfig Website Management</module_title>
    
    <!-- Allgemeine Texte -->
    <websites>Websites</websites>
    <databases>Datenbanken</databases>
    <email_accounts>E-Mail-Konten</email_accounts>
    <ftp_users>FTP-Benutzer</ftp_users>
    <subdomains>Subdomains</subdomains>
    <clients>Kunden</clients>
    
    <!-- Aktionen -->
    <create_website>Website erstellen</create_website>
    <edit_website>Website bearbeiten</edit_website>
    <delete_website>Website löschen</delete_website>
    <create_database>Datenbank erstellen</create_database>
    <create_email>E-Mail-Konto erstellen</create_email>
    <create_ftp_user>FTP-Benutzer erstellen</create_ftp_user>
    <create_subdomain>Subdomain erstellen</create_subdomain>
    
    <!-- Formular-Felder -->
    <domain>Domain</domain>
    <ip_address>IP-Adresse</ip_address>
    <system_user>System-Benutzer</system_user>
    <system_group>System-Gruppe</system_group>
    <quota>Quota</quota>
    <traffic>Traffic</traffic>
    <php_version>PHP-Version</php_version>
    <ssl>SSL</ssl>
    <backup>Backup</backup>
    <description>Beschreibung</description>
    
    <!-- Status -->
    <active>Aktiv</active>
    <inactive>Inaktiv</inactive>
    <suspended>Suspendiert</suspended>
    <pending>Ausstehend</pending>
    
    <!-- Erfolgsmeldungen -->
    <website_created_successfully>Website erfolgreich erstellt</website_created_successfully>
    <website_updated_successfully>Website erfolgreich aktualisiert</website_updated_successfully>
    <website_deleted_successfully>Website erfolgreich gelöscht</website_deleted_successfully>
    <database_created_successfully>Datenbank erfolgreich erstellt</database_created_successfully>
    <email_created_successfully>E-Mail-Konto erfolgreich erstellt</email_created_successfully>
    <ftp_user_created_successfully>FTP-Benutzer erfolgreich erstellt</ftp_user_created_successfully>
    <subdomain_created_successfully>Subdomain erfolgreich erstellt</subdomain_created_successfully>
    
    <!-- Fehlermeldungen -->
    <error_creating_website>Fehler beim Erstellen der Website</error_creating_website>
    <error_updating_website>Fehler beim Aktualisieren der Website</error_updating_website>
    <error_deleting_website>Fehler beim Löschen der Website</error_deleting_website>
    <error_getting_clients>Fehler beim Abrufen der Kunden</error_getting_clients>
    <error_getting_server_config>Fehler beim Abrufen der Server-Konfiguration</error_getting_server_config>
    <error_getting_website_details>Fehler beim Abrufen der Website-Details</error_getting_website_details>
    <error_creating_database>Fehler beim Erstellen der Datenbank</error_creating_database>
    <error_creating_email>Fehler beim Erstellen des E-Mail-Kontos</error_creating_email>
    <error_creating_ftp_user>Fehler beim Erstellen des FTP-Benutzers</error_creating_ftp_user>
    <error_creating_subdomain>Fehler beim Erstellen der Subdomain</error_creating_subdomain>
    
    <!-- Buttons -->
    <create>Erstellen</create>
    <edit>Bearbeiten</edit>
    <delete>Löschen</delete>
    <save>Speichern</save>
    <cancel>Abbrechen</cancel>
    <refresh>Aktualisieren</refresh>
    <view>Anzeigen</view>
    <confirm>Bestätigen</confirm>
    
    <!-- Bestätigungsdialoge -->
    <confirm_delete_website>Möchten Sie diese Website wirklich löschen?</confirm_delete_website>
    <confirm_delete_database>Möchten Sie diese Datenbank wirklich löschen?</confirm_delete_database>
    <confirm_delete_email>Möchten Sie dieses E-Mail-Konto wirklich löschen?</confirm_delete_email>
    
    <!-- Tabellen-Header -->
    <domain_name>Domain</domain_name>
    <ip>IP-Adresse</ip>
    <status>Status</status>
    <quota_usage>Quota-Nutzung</quota_usage>
    <traffic_usage>Traffic-Nutzung</traffic_usage>
    <created>Erstellt</created>
    <updated>Aktualisiert</updated>
    <actions>Aktionen</actions>
    
    <!-- Einheiten -->
    <mb>MB</mb>
    <gb>GB</gb>
    <percent>%</percent>
    
    <!-- Platzhalter -->
    <enter_domain>Domain eingeben</enter_domain>
    <enter_ip_address>IP-Adresse eingeben</enter_ip_address>
    <enter_system_user>System-Benutzer eingeben</enter_system_user>
    <enter_system_group>System-Gruppe eingeben</enter_system_group>
    <select_php_version>PHP-Version auswählen</select_php_version>
    
    <!-- Validierung -->
    <domain_required>Domain ist erforderlich</domain_required>
    <ip_address_required>IP-Adresse ist erforderlich</ip_address_required>
    <system_user_required>System-Benutzer ist erforderlich</system_user_required>
    <system_group_required>System-Gruppe ist erforderlich</system_group_required>
    <quota_required>Quota ist erforderlich</quota_required>
    <traffic_required>Traffic ist erforderlich</traffic_required>
    <invalid_domain>Ungültige Domain</invalid_domain>
    <invalid_ip_address>Ungültige IP-Adresse</invalid_ip_address>
    <invalid_quota>Ungültige Quota</invalid_quota>
    <invalid_traffic>Ungültiger Traffic</invalid_traffic>
    
    <!-- Allgemeine Texte -->
    <loading>Laden...</loading>
    <operation_successful>Operation erfolgreich</operation_successful>
    <operation_failed>Operation fehlgeschlagen</operation_failed>
    <validation_failed>Validierung fehlgeschlagen</validation_failed>
    <unknown_action>Unbekannte Aktion</unknown_action>
    <create_website_ispconfig>Website in ISPConfig erstellen</create_website_ispconfig>
    <hd_quota>HD Quota (MB)</hd_quota>
    <traffic_quota>Traffic Quota (MB)</traffic_quota>
    <domain_id>Domain ID</domain_id>
    <ftp_username>FTP Username</ftp_username>
    <parent_domain_id>Parent Domain ID</parent_domain_id>
    <subdomain>Subdomain</subdomain>
    <redirect_type>Redirect Type</redirect_type>
    <no_redirect>Kein Redirect</no_redirect>
    <redirect_temporary>R (Temporary)</redirect_temporary>
    <redirect_permanent>L (Permanent)</redirect_permanent>
    <redirect_path>Redirect Path (optional)</redirect_path>
    <quick_actions>Schnellaktionen</quick_actions>
    <load_clients>Clients laden</load_clients>
    <server_config>Server Config</server_config>
    <website_details>Website Details</website_details>
    <clients_loaded>Clients geladen - siehe Konsole</clients_loaded>
    <server_config_loaded>Server Config geladen - siehe Konsole</server_config_loaded>
    <website_details_loaded>Website Details geladen - siehe Konsole</website_details_loaded>
    <enter_domain_id>Bitte Domain ID eingeben</enter_domain_id>
    <network_error>Netzwerkfehler</network_error>
    <unknown_error>Unbekannter Fehler</unknown_error>
    <website_created_message>Website wurde erfolgreich erstellt!</website_created_message>
    <ftp_user_created_message>FTP-Benutzer wurde erfolgreich erstellt!</ftp_user_created_message>
    <subdomain_created_message>Subdomain wurde erfolgreich erstellt!</subdomain_created_message>
    
    <!-- Benutzer-Management -->
    <users_overview>Benutzer-Übersicht</users_overview>
    <user_details>Benutzer-Details</user_details>
    <user_information>Benutzer-Informationen</user_information>
    <statistics>Statistiken</statistics>
    <search_users>Benutzer suchen...</search_users>
    <all_status>Alle Status</all_status>
    <sort_by_company>Nach Firma sortieren</sort_by_company>
    <sort_by_contact>Nach Kontakt sortieren</sort_by_contact>
    <sort_by_date>Nach Datum sortieren</sort_by_date>
    <clear_filters>Filter zurücksetzen</clear_filters>
    <loading_users>Benutzer werden geladen...</loading_users>
    <no_users_found>Keine Benutzer gefunden</no_users_found>
    <client_id>Client ID</client_id>
    <company_name>Firma</company_name>
    <contact_name>Kontakt</contact_name>
    <email>E-Mail</email>
    <phone>Telefon</phone>
    <street>Straße</street>
    <city>Stadt</city>
    <zip>PLZ</zip>
    <country>Land</country>
    <created_at>Erstellt</created_at>
    <close>Schließen</close>
    
    <!-- E-Mail-Management -->
    <login_name>Login-Name</login_name>
    <quota_mb>Quota (MB)</quota_mb>
    <spam_filter>Spam-Filter</spam_filter>
    
    <!-- Datenbank-Management -->
    <database_name>Datenbank-Name</database_name>
    <database_user>Datenbank-Benutzer</database_user>
    <database_type>Datenbank-Typ</database_type>
    
    <!-- FTP-Management -->
    <username>Benutzername</username>
    <quota_size>Quota-Größe</quota_size>
    <directory>Verzeichnis</directory>
    
    <!-- Fehlermeldungen für Benutzer-Management -->
    <error_getting_users>Fehler beim Abrufen der Benutzer</error_getting_users>
    <user_not_found>Benutzer nicht gefunden</user_not_found>
    
    <!-- Domain-Management -->
    <domain_management>Domain-Management</domain_management>
    <search_domains>Domains suchen...</search_domains>
    <all_assignments>Alle Zuordnungen</all_assignments>
    <assigned>Zugewiesen</assigned>
    <unassigned>Nicht zugewiesen</unassigned>
    <sort_by_domain>Nach Domain sortieren</sort_by_domain>
    <sort_by_user>Nach Benutzer sortieren</sort_by_user>
    <loading_domains>Domains werden geladen...</loading_domains>
    <no_domains_found>Keine Domains gefunden</no_domains_found>
    <assigned_user>Zugewiesener Benutzer</assigned_user>
    <ssl_enabled>SSL aktiviert</ssl_enabled>
    <enabled>Aktiviert</enabled>
    <disabled>Deaktiviert</enabled>
    
    <!-- Domain-Zuordnung -->
    <assign_domain_to_user>Domain Benutzer zuweisen</assign_domain_to_user>
    <select_user>Benutzer auswählen</select_user>
    <select_user_placeholder>Benutzer auswählen...</select_user_placeholder>
    <notes>Notizen</notes>
    <assignment_notes_placeholder>Optionale Notizen zur Zuweisung...</assignment_notes_placeholder>
    <assign>Zuweisen</assign>
    
    <!-- Domain-Einstellungen -->
    <domain_settings>Domain-Einstellungen</domain_settings>
    <save_changes>Änderungen speichern</save_changes>
    
    <!-- Bulk-Änderungen -->
    <bulk_changes>Bulk-Änderungen</bulk_changes>
    <preview_changes>Änderungs-Vorschau</preview_changes>
    <total_changes>Gesamt Änderungen</total_changes>
    <affected_users>Betroffene Benutzer</affected_users>
    <affected_domains>Betroffene Domains</affected_domains>
    <changes_details>Änderungsdetails</changes_details>
    <execute_changes>Änderungen ausführen</execute_changes>
    
    <!-- Erfolgs- und Fehlermeldungen für Domain-Management -->
    <domain_assigned_successfully>Domain erfolgreich zugewiesen</domain_assigned_successfully>
    <domain_unassigned_successfully>Domain-Zuweisung erfolgreich entfernt</domain_unassigned_successfully>
    <domain_settings_updated_successfully>Domain-Einstellungen erfolgreich aktualisiert</domain_settings_updated_successfully>
    <error_getting_domains>Fehler beim Abrufen der Domains</error_getting_domains>
    <domain_not_found>Domain nicht gefunden</domain_not_found>
    
    <!-- DNS-Management -->
    <dns_management>DNS-Management</dns_management>
    <combined_view>Kombinierte Ansicht</combined_view>
    <add_dns_record>DNS-Eintrag hinzufügen</add_dns_record>
    <sync_dns_records>DNS synchronisieren</sync_dns_records>
    <loading_dns_records>DNS-Einträge werden geladen...</loading_dns_records>
    <no_dns_records_found>Keine DNS-Einträge gefunden</no_dns_records_found>
    <type>Typ</type>
    <name>Name</name>
    <value>Wert</value>
    <ttl>TTL</ttl>
    <priority>Priorität</priority>
    <source>Quelle</source>
    <edit_dns_record>DNS-Eintrag bearbeiten</edit_dns_record>
    <delete>Löschen</delete>
    <save>Speichern</save>
    <close>Schließen</close>
    
    <!-- DNS-Synchronisation -->
    <dns_synchronisation>DNS-Synchronisation</dns_synchronisation>
    <sync_direction>Synchronisationsrichtung</sync_direction>
    <warning>Warnung</warning>
    <dns_sync_warning>Die Synchronisation kann bestehende DNS-Einträge überschreiben. Stellen Sie sicher, dass Sie eine Sicherung haben.</dns_sync_warning>
    <sync_preview>Synchronisations-Vorschau</sync_preview>
    <execute_sync>Synchronisation ausführen</execute_sync>
    
    <!-- Erfolgs- und Fehlermeldungen für DNS-Management -->
    <dns_record_updated_successfully>DNS-Eintrag erfolgreich aktualisiert</dns_record_updated_successfully>
    <dns_record_created_successfully>DNS-Eintrag erfolgreich erstellt</dns_record_created_successfully>
    <dns_record_deleted_successfully>DNS-Eintrag erfolgreich gelöscht</dns_record_deleted_successfully>
    <dns_sync_completed_successfully>DNS-Synchronisation erfolgreich abgeschlossen</dns_sync_completed_successfully>
    <error_getting_dns_records>Fehler beim Abrufen der DNS-Einträge</error_getting_dns_records>
    <error_getting_ovh_dns_records>Fehler beim Abrufen der OVH DNS-Einträge</error_getting_ovh_dns_records>
    <error_updating_dns_record>Fehler beim Aktualisieren des DNS-Eintrags</error_updating_dns_record>
    <error_creating_dns_record>Fehler beim Erstellen des DNS-Eintrags</error_creating_dns_record>
    <error_deleting_dns_record>Fehler beim Löschen des DNS-Eintrags</error_deleting_dns_record>
    <error_syncing_dns_records>Fehler bei der DNS-Synchronisation</error_syncing_dns_records>
    <dns_record_not_found>DNS-Eintrag nicht gefunden</dns_record_not_found>
    <dns_zone_not_found>DNS-Zone nicht gefunden</dns_zone_not_found>
    <invalid_dns_source>Ungültige DNS-Quelle</invalid_dns_source>
</translations> 